franky/__init__.py
franky/_franky.cpython-313-x86_64-linux-gnu.so
franky/_franky.pyi
franky/motion.py
franky/reaction.py
franky/robot.py
franky/robot_web_session.py
franky_control.libs/libPocoFoundation-31c294b8.so.95
franky_control.libs/libPocoNet-e2d7659c.so.95
franky_control.libs/libboost_filesystem-0bf67256.so.1.75.0
franky_control.libs/libboost_serialization-67da18f6.so.1.75.0
franky_control.libs/libconsole_bridge-acce180d.so.1.0
franky_control.libs/libfmt-677b7a5c.so.8.1.1
franky_control.libs/libfranka-0438a9f0.so.0.15.3
franky_control.libs/libpinocchio_default-c77daf45.so.3.1.0
franky_control.libs/libpinocchio_parsers-cbd23136.so.3.1.0
franky_control.libs/libtinyxml-69e5f0dd.so.0.2.6.2
franky_control.libs/liburdfdom_model-9ec0392f.so.1.0
franky_control.libs/liburdfdom_model_state-01125232.so.1.0
franky_control.libs/liburdfdom_sensor-011819fa.so.1.0
franky_control.libs/liburdfdom_world-4d53bc81.so.1.0
franky_control-1.1.2.dist-info/METADATA
franky_control-1.1.2.dist-info/WHEEL
franky_control-1.1.2.dist-info/top_level.txt
franky_control-1.1.2.dist-info/RECORD
franky_control-1.1.2.dist-info/licenses/LICENSE
