Metadata-Version: 2.4
Name: franky-control
Version: 1.1.2
Summary: High-level control library for Franka robots.
Home-page: https://github.com/TimSchneider42/franky
Author: Tim Schneider
Author-email: tim@robot-learning.de
License: LGPL-3.0-or-later
Keywords: control,robotics,franka,franka-panda,franka-research-3
Classifier: Development Status :: 4 - Beta
Classifier: Intended Audience :: Science/Research
Classifier: Topic :: Scientific/Engineering
Classifier: Programming Language :: C++
Requires-Python: >=3.7
License-File: LICENSE
Requires-Dist: numpy
Dynamic: author
Dynamic: author-email
Dynamic: classifier
Dynamic: description
Dynamic: description-content-type
Dynamic: home-page
Dynamic: keywords
Dynamic: license
Dynamic: license-file
Dynamic: requires-dist
Dynamic: requires-python
Dynamic: summary
